liebnizlib/__init__.py
liebnizlib/config.py
liebnizlib/liebniz.py
liebnizlib/utilities.py
tests/__init__.py
tests/test_liebniz.py
liebniz-1.0.0.dist-info/LICENSE
liebniz-1.0.0.dist-info/METADATA
liebniz-1.0.0.dist-info/WHEEL
liebniz-1.0.0.dist-info/top_level.txt
liebniz-1.0.0.dist-info/RECORD
