Metadata-Version: 2.1
Name: liebniz
Version: 1.0.0
Summary: Leibniz Secure Algorithm (LSA) implementation
Home-page: https://github.com/Marvex18/leibniz
Author: Akinsunlade Marvelous
Author-email: akinmarvelous2022@gmail.com
Classifier: Programming Language :: Python :: 3
Classifier: License :: OSI Approved :: MIT License
Classifier: Operating System :: OS Independent
Requires-Python: >=3.6
License-File: LICENSE
Requires-Dist: numpy
